countdown_event/__init__.py
countdown_event-0.1.0.dist-info/LICENSE
countdown_event-0.1.0.dist-info/WHEEL
countdown_event-0.1.0.dist-info/METADATA
countdown_event-0.1.0.dist-info/RECORD
