Metadata-Version: 2.1
Name: countdown-event
Version: 0.1.0
Summary: An asyncio event which blocks until the count reaches zero
Home-page: https://github.com/rob-blackbourn/countdown-event
License: Apache-2.0
Author: Rob Blackbourn
Author-email: rob.blackbourn@gmail.com
Requires-Python: >=3.7,<4.0
Classifier: License :: OSI Approved :: Apache Software License
Classifier: Programming Language :: Python :: 3
Classifier: Programming Language :: Python :: 3.7
Project-URL: Repository, https://github.com/rob-blackbourn/countdown-event
